{
  "batchId": "reg-batch-003",
  "section": "REG",
  "topic": "Individual Taxation - Itemized Deductions",
  "totalQuestions": 35,
  "difficultyMix": {
    "easy": 6,
    "medium": 15,
    "hard": 14
  },
  "questions": [
    {
      "id": "reg-003-001",
      "section": "REG",
      "topic": "Individual Taxation",
      "subtopic": "Itemized Deductions",
      "conceptTested": "Standard vs itemized deduction choice",
      "difficulty": "easy",
      "questionFormat": "MCQ",
      "question": "A taxpayer should itemize deductions when:",
      "options": {
        "A": "They own a home",
        "B": "Total itemized deductions exceed the standard deduction",
        "C": "They have any medical expenses",
        "D": "Their AGI exceeds $100,000"
      },
      "correctAnswer": "B",
      "explanation": "Taxpayers should itemize when their total itemized deductions exceed the standard deduction. After TCJA nearly doubled the standard deduction, fewer taxpayers benefit from itemizing. The decision is purely mathematical—choose the larger deduction.",
      "tip": "Itemize only if total itemized > standard deduction. Do the math.",
      "calculationRequired": false,
      "timeEstimateSeconds": 45
    },
    {
      "id": "reg-003-002",
      "section": "REG",
      "topic": "Individual Taxation",
      "subtopic": "Itemized Deductions",
      "conceptTested": "2023 standard deduction amounts",
      "difficulty": "easy",
      "questionFormat": "MCQ",
      "question": "The 2023 standard deduction for married filing jointly is:",
      "options": {
        "A": "$13,850",
        "B": "$20,800",
        "C": "$27,700",
        "D": "$30,000"
      },
      "correctAnswer": "C",
      "explanation": "For 2023, the standard deduction is $27,700 for married filing jointly, $13,850 for single and married filing separately, and $20,800 for head of household. These amounts are indexed annually for inflation.",
      "tip": "2023 standard deduction: $27,700 MFJ, $20,800 HoH, $13,850 single/MFS.",
      "calculationRequired": false,
      "timeEstimateSeconds": 45
    },
    {
      "id": "reg-003-003",
      "section": "REG",
      "topic": "Individual Taxation",
      "subtopic": "Itemized Deductions",
      "conceptTested": "Medical expense threshold",
      "difficulty": "easy",
      "questionFormat": "MCQ",
      "question": "Medical expenses are deductible to the extent they exceed:",
      "options": {
        "A": "2% of AGI",
        "B": "7.5% of AGI",
        "C": "10% of AGI",
        "D": "$1,000"
      },
      "correctAnswer": "B",
      "explanation": "Medical and dental expenses are deductible as itemized deductions to the extent they exceed 7.5% of AGI. This threshold was made permanent at 7.5% after fluctuating between 7.5% and 10% in prior years.",
      "tip": "Medical deduction = expenses exceeding 7.5% of AGI.",
      "calculationRequired": false,
      "timeEstimateSeconds": 45
    },
    {
      "id": "reg-003-004",
      "section": "REG",
      "topic": "Individual Taxation",
      "subtopic": "Itemized Deductions",
      "conceptTested": "Mortgage interest deduction",
      "difficulty": "easy",
      "questionFormat": "MCQ",
      "question": "Home mortgage interest is deductible on acquisition debt up to:",
      "options": {
        "A": "$500,000",
        "B": "$750,000 for loans originated after December 15, 2017",
        "C": "$1,000,000 for all loans",
        "D": "$2,000,000"
      },
      "correctAnswer": "B",
      "explanation": "For mortgages originated after December 15, 2017, interest is deductible on acquisition debt up to $750,000 ($375,000 MFS). Loans originated before that date are grandfathered at the $1,000,000 limit. Home equity loan interest is only deductible if used to buy, build, or improve the home.",
      "tip": "Mortgage interest: $750K limit for post-12/15/2017 loans; $1M grandfathered.",
      "calculationRequired": false,
      "timeEstimateSeconds": 45
    },
    {
      "id": "reg-003-005",
      "section": "REG",
      "topic": "Individual Taxation",
      "subtopic": "Itemized Deductions",
      "conceptTested": "SALT deduction cap",
      "difficulty": "easy",
      "questionFormat": "MCQ",
      "question": "The state and local tax (SALT) deduction is limited to:",
      "options": {
        "A": "$5,000",
        "B": "$10,000 ($5,000 if married filing separately)",
        "C": "$15,000",
        "D": "No limit"
      },
      "correctAnswer": "B",
      "explanation": "TCJA imposed a $10,000 cap ($5,000 MFS) on the combined deduction for state and local income taxes (or sales taxes) and property taxes. This limit applies through 2025 and significantly impacts taxpayers in high-tax states.",
      "tip": "SALT cap: $10,000 total ($5,000 MFS) for state/local income + property taxes.",
      "calculationRequired": false,
      "timeEstimateSeconds": 45
    },
    {
      "id": "reg-003-006",
      "section": "REG",
      "topic": "Individual Taxation",
      "subtopic": "Itemized Deductions",
      "conceptTested": "Charitable contribution limits",
      "difficulty": "easy",
      "questionFormat": "MCQ",
      "question": "Cash contributions to public charities are generally deductible up to:",
      "options": {
        "A": "30% of AGI",
        "B": "50% of AGI",
        "C": "60% of AGI",
        "D": "100% of AGI"
      },
      "correctAnswer": "C",
      "explanation": "Cash contributions to public charities (50% organizations) are deductible up to 60% of AGI under TCJA through 2025 (increased from 50%). Contributions of appreciated property are limited to 30% of AGI. Lower limits apply to private foundations.",
      "tip": "Charitable cash: 60% AGI limit (through 2025). Appreciated property: 30% AGI limit.",
      "calculationRequired": false,
      "timeEstimateSeconds": 45
    },
    {
      "id": "reg-003-007",
      "section": "REG",
      "topic": "Individual Taxation",
      "subtopic": "Itemized Deductions",
      "conceptTested": "Qualifying medical expenses",
      "difficulty": "medium",
      "questionFormat": "MCQ",
      "question": "Which of the following is a deductible medical expense?",
      "options": {
        "A": "Cosmetic surgery for personal appearance",
        "B": "Health club membership for general fitness",
        "C": "Prescription medications and insulin",
        "D": "Over-the-counter vitamins"
      },
      "correctAnswer": "C",
      "explanation": "Prescription medications and insulin are deductible medical expenses. Cosmetic surgery (unless for disfigurement from disease, accident, or congenital abnormality), gym memberships for general health, and non-prescription vitamins are not deductible.",
      "tip": "Deductible medical: prescriptions, doctor visits, hospital. NOT gym, cosmetics, vitamins.",
      "calculationRequired": false,
      "timeEstimateSeconds": 60
    },
    {
      "id": "reg-003-008",
      "section": "REG",
      "topic": "Individual Taxation",
      "subtopic": "Itemized Deductions",
      "conceptTested": "Capital gains property contributions",
      "difficulty": "medium",
      "questionFormat": "MCQ",
      "question": "When contributing long-term capital gain property to a public charity, the deduction is generally:",
      "options": {
        "A": "Limited to the taxpayer's basis",
        "B": "Fair market value, limited to 30% of AGI",
        "C": "Fair market value, limited to 50% of AGI",
        "D": "Not deductible"
      },
      "correctAnswer": "B",
      "explanation": "Long-term capital gain property contributed to a public charity is deductible at fair market value (no gain recognition), but the deduction is limited to 30% of AGI. The taxpayer can elect to use basis and get the 50% limit instead.",
      "tip": "LTCG property to charity: FMV deduction at 30% limit, or elect basis at 50% limit.",
      "calculationRequired": false,
      "timeEstimateSeconds": 60
    },
    {
      "id": "reg-003-009",
      "section": "REG",
      "topic": "Individual Taxation",
      "subtopic": "Itemized Deductions",
      "conceptTested": "Investment interest expense",
      "difficulty": "medium",
      "questionFormat": "MCQ",
      "question": "Investment interest expense is deductible to the extent of:",
      "options": {
        "A": "Total AGI",
        "B": "Net investment income",
        "C": "$10,000",
        "D": "Mortgage interest paid"
      },
      "correctAnswer": "B",
      "explanation": "Investment interest expense (interest on loans to purchase taxable investments) is deductible as an itemized deduction only to the extent of net investment income. Excess interest carries forward indefinitely to future years.",
      "tip": "Investment interest limited to net investment income. Excess carries forward.",
      "calculationRequired": false,
      "timeEstimateSeconds": 60
    },
    {
      "id": "reg-003-010",
      "section": "REG",
      "topic": "Individual Taxation",
      "subtopic": "Itemized Deductions",
      "conceptTested": "Casualty loss deduction",
      "difficulty": "medium",
      "questionFormat": "MCQ",
      "question": "Under current law, personal casualty losses are deductible only if:",
      "options": {
        "A": "They exceed $100 per casualty",
        "B": "They result from a federally declared disaster",
        "C": "They exceed 10% of AGI",
        "D": "The taxpayer has insurance"
      },
      "correctAnswer": "B",
      "explanation": "TCJA limits personal casualty loss deductions to losses from federally declared disasters only (2018-2025). The loss must exceed $500 per casualty (increased from $100 by TCJA under IRC §165(h)(5)) and total losses must exceed 10% of AGI. Casualty gains can offset non-disaster losses.",
      "tip": "Personal casualty loss: federal disaster only (TCJA). Still need $500 + 10% AGI floors.",
      "calculationRequired": false,
      "timeEstimateSeconds": 60
    },
    {
      "id": "reg-003-011",
      "section": "REG",
      "topic": "Individual Taxation",
      "subtopic": "Itemized Deductions",
      "conceptTested": "Gambling losses",
      "difficulty": "medium",
      "questionFormat": "MCQ",
      "question": "Gambling losses are deductible:",
      "options": {
        "A": "Without limitation",
        "B": "Only to the extent of gambling winnings",
        "C": "Up to $3,000 per year",
        "D": "Only if the taxpayer is a professional gambler"
      },
      "correctAnswer": "B",
      "explanation": "Gambling losses are deductible as an itemized deduction, but only to the extent of gambling winnings reported as income. Gambling winnings must be reported in full; losses cannot create a net deduction.",
      "tip": "Gambling losses limited to winnings. Report all winnings, deduct losses up to that amount.",
      "calculationRequired": false,
      "timeEstimateSeconds": 60
    },
    {
      "id": "reg-003-012",
      "section": "REG",
      "topic": "Individual Taxation",
      "subtopic": "Itemized Deductions",
      "conceptTested": "Charitable contribution substantiation",
      "difficulty": "medium",
      "questionFormat": "MCQ",
      "question": "For a cash charitable contribution of $300, the taxpayer must have:",
      "options": {
        "A": "No documentation required",
        "B": "A bank record or written receipt from the charity",
        "C": "A written appraisal",
        "D": "Form 8283"
      },
      "correctAnswer": "B",
      "explanation": "All cash contributions, regardless of amount, require a bank record (canceled check, credit card statement) or written communication from the charity showing the amount and date. Contributions of $250 or more require a contemporaneous written acknowledgment.",
      "tip": "Cash charity: bank record or receipt for any amount. $250+ needs written acknowledgment.",
      "calculationRequired": false,
      "timeEstimateSeconds": 60
    },
    {
      "id": "reg-003-013",
      "section": "REG",
      "topic": "Individual Taxation",
      "subtopic": "Itemized Deductions",
      "conceptTested": "Donation of clothing and household items",
      "difficulty": "medium",
      "questionFormat": "MCQ",
      "question": "Donated clothing and household items are deductible only if:",
      "options": {
        "A": "They cost more than $500 originally",
        "B": "They are in good used condition or better",
        "C": "The taxpayer has owned them for more than one year",
        "D": "They are donated to a public charity"
      },
      "correctAnswer": "B",
      "explanation": "Donated clothing and household items must be in good used condition or better to be deductible. A deduction may be allowed for items not in good condition if the deduction exceeds $500 and a qualified appraisal is obtained.",
      "tip": "Donated clothes/household items: must be in good condition (or get appraisal if >$500).",
      "calculationRequired": false,
      "timeEstimateSeconds": 60
    },
    {
      "id": "reg-003-014",
      "section": "REG",
      "topic": "Individual Taxation",
      "subtopic": "Itemized Deductions",
      "conceptTested": "Charitable mileage rate",
      "difficulty": "medium",
      "questionFormat": "MCQ",
      "question": "The standard mileage rate for charitable purposes is:",
      "options": {
        "A": "14 cents per mile",
        "B": "22 cents per mile",
        "C": "56 cents per mile",
        "D": "65.5 cents per mile"
      },
      "correctAnswer": "A",
      "explanation": "The charitable mileage rate is set by statute at 14 cents per mile and does not change with inflation. This is significantly lower than the business mileage rate (65.5 cents for 2023) or medical/moving rate (22 cents for 2023).",
      "tip": "Charity mileage = 14 cents (fixed by statute). Much lower than business rate.",
      "calculationRequired": false,
      "timeEstimateSeconds": 60
    },
    {
      "id": "reg-003-015",
      "section": "REG",
      "topic": "Individual Taxation",
      "subtopic": "Itemized Deductions",
      "conceptTested": "Points on home purchase",
      "difficulty": "medium",
      "questionFormat": "MCQ",
      "question": "Points paid on the purchase of a principal residence are:",
      "options": {
        "A": "Never deductible",
        "B": "Deductible in the year paid if certain requirements are met",
        "C": "Always amortized over the loan term",
        "D": "Deductible only if paid by the seller"
      },
      "correctAnswer": "B",
      "explanation": "Points paid on the purchase of a principal residence are generally fully deductible in the year paid if: (1) the loan is secured by the principal residence, (2) points are computed as a percentage of the loan, (3) charging points is an established practice in the area, and (4) points don't exceed typical amounts.",
      "tip": "Points on home purchase = deduct in year paid (if typical and meets requirements).",
      "calculationRequired": false,
      "timeEstimateSeconds": 60
    },
    {
      "id": "reg-003-016",
      "section": "REG",
      "topic": "Individual Taxation",
      "subtopic": "Itemized Deductions",
      "conceptTested": "Points on refinance",
      "difficulty": "medium",
      "questionFormat": "MCQ",
      "question": "Points paid on refinancing a home mortgage are:",
      "options": {
        "A": "Fully deductible in the year paid",
        "B": "Amortized over the life of the new loan",
        "C": "Not deductible",
        "D": "Deductible only if the loan increases"
      },
      "correctAnswer": "B",
      "explanation": "Points paid on a refinanced mortgage must be amortized over the life of the loan. However, if the refinance is on the principal residence and part of the proceeds are used for home improvements, that portion of points may be currently deductible.",
      "tip": "Refinance points = amortize over loan life. Purchase points = deduct immediately.",
      "calculationRequired": false,
      "timeEstimateSeconds": 60
    },
    {
      "id": "reg-003-017",
      "section": "REG",
      "topic": "Individual Taxation",
      "subtopic": "Itemized Deductions",
      "conceptTested": "State income vs sales tax",
      "difficulty": "medium",
      "questionFormat": "MCQ",
      "question": "Under the SALT deduction, taxpayers may deduct:",
      "options": {
        "A": "Both state income taxes and state sales taxes",
        "B": "State income taxes OR state sales taxes, but not both",
        "C": "Only state income taxes",
        "D": "Only property taxes"
      },
      "correctAnswer": "B",
      "explanation": "Taxpayers may deduct either state and local income taxes or state and local sales taxes, but not both. Those in states without income tax (like Texas or Florida) often benefit from deducting sales taxes. Either choice is combined with property taxes for the $10,000 SALT cap.",
      "tip": "SALT: choose income tax OR sales tax (not both), plus property tax. Total capped at $10K.",
      "calculationRequired": false,
      "timeEstimateSeconds": 60
    },
    {
      "id": "reg-003-018",
      "section": "REG",
      "topic": "Individual Taxation",
      "subtopic": "Itemized Deductions",
      "conceptTested": "Charitable carryover",
      "difficulty": "medium",
      "questionFormat": "MCQ",
      "question": "Excess charitable contributions that exceed the AGI limitation may be:",
      "options": {
        "A": "Lost permanently",
        "B": "Carried forward for 5 years",
        "C": "Carried back 2 years",
        "D": "Carried forward for 10 years"
      },
      "correctAnswer": "B",
      "explanation": "Charitable contributions exceeding the applicable AGI percentage limitation (60%, 50%, 30%, or 20%) may be carried forward for 5 years. Carryovers are used after current year contributions and retain their original character.",
      "tip": "Excess charitable contributions: 5-year carryforward. Used after current year gifts.",
      "calculationRequired": false,
      "timeEstimateSeconds": 60
    },
    {
      "id": "reg-003-019",
      "section": "REG",
      "topic": "Individual Taxation",
      "subtopic": "Itemized Deductions",
      "conceptTested": "Medical expense timing",
      "difficulty": "medium",
      "questionFormat": "MCQ",
      "question": "Medical expenses paid by credit card are deductible:",
      "options": {
        "A": "When the credit card bill is paid",
        "B": "In the year the charge is made",
        "C": "Over the period the payments are made",
        "D": "Only in the year the medical service is received"
      },
      "correctAnswer": "B",
      "explanation": "Medical expenses paid by credit card are deductible in the year the charge is made, not when the credit card bill is paid. The credit card company pays the provider, creating an obligation to the credit card company, which is considered payment.",
      "tip": "Credit card medical expenses: deduct when charged, not when card is paid off.",
      "calculationRequired": false,
      "timeEstimateSeconds": 60
    },
    {
      "id": "reg-003-020",
      "section": "REG",
      "topic": "Individual Taxation",
      "subtopic": "Itemized Deductions",
      "conceptTested": "Real property taxes",
      "difficulty": "medium",
      "questionFormat": "MCQ",
      "question": "Real property taxes are deductible by:",
      "options": {
        "A": "Only the person whose name is on the deed",
        "B": "The person who pays them, even if not the owner",
        "C": "The owner of the property who pays them",
        "D": "Only if the property is a principal residence"
      },
      "correctAnswer": "C",
      "explanation": "Real property taxes are deductible by the owner who pays them. A tenant paying property taxes on behalf of a landlord cannot deduct them. If property is sold mid-year, taxes are prorated between buyer and seller based on ownership period.",
      "tip": "Property taxes: owner who pays can deduct. Prorate on sale.",
      "calculationRequired": false,
      "timeEstimateSeconds": 60
    },
    {
      "id": "reg-003-021",
      "section": "REG",
      "topic": "Individual Taxation",
      "subtopic": "Itemized Deductions",
      "conceptTested": "Vehicle donation rules",
      "difficulty": "medium",
      "questionFormat": "MCQ",
      "question": "For a donated vehicle worth more than $500, the charitable deduction is generally:",
      "options": {
        "A": "Fair market value",
        "B": "Limited to the gross proceeds from the charity's sale of the vehicle",
        "C": "The taxpayer's basis in the vehicle",
        "D": "Blue book value"
      },
      "correctAnswer": "B",
      "explanation": "For donated vehicles worth more than $500, the deduction is generally limited to the gross proceeds from the charity's sale. Exceptions allow FMV if the charity materially improves the vehicle or uses it substantially for charitable purposes.",
      "tip": "Vehicle donation >$500: deduction = what charity sells it for (unless they use/improve it).",
      "calculationRequired": false,
      "timeEstimateSeconds": 60
    },
    {
      "id": "reg-003-022",
      "section": "REG",
      "topic": "Individual Taxation",
      "subtopic": "Itemized Deductions",
      "conceptTested": "Private foundation contributions",
      "difficulty": "hard",
      "questionFormat": "MCQ",
      "question": "Cash contributions to private non-operating foundations are limited to:",
      "options": {
        "A": "60% of AGI",
        "B": "50% of AGI",
        "C": "30% of AGI",
        "D": "20% of AGI"
      },
      "correctAnswer": "C",
      "explanation": "Cash contributions to private non-operating foundations are limited to 30% of AGI (vs. 60% for public charities). Contributions of appreciated property to private foundations are generally limited to 20% of AGI and deductible at basis, not FMV.",
      "tip": "Private foundation limits: cash = 30% AGI; appreciated property = 20% AGI at basis.",
      "calculationRequired": false,
      "timeEstimateSeconds": 75
    },
    {
      "id": "reg-003-023",
      "section": "REG",
      "topic": "Individual Taxation",
      "subtopic": "Itemized Deductions",
      "conceptTested": "Quid pro quo contributions",
      "difficulty": "hard",
      "questionFormat": "MCQ",
      "question": "When a donor receives goods or services in exchange for a contribution, the deduction is:",
      "options": {
        "A": "The full amount paid",
        "B": "The amount paid minus the fair market value of goods/services received",
        "C": "Zero, because it is not a true contribution",
        "D": "The fair market value of goods/services received"
      },
      "correctAnswer": "B",
      "explanation": "For quid pro quo contributions (where donor receives something in return), only the excess of the payment over the FMV of goods or services received is deductible. Charities must provide written disclosure for payments over $75.",
      "tip": "Quid pro quo: deduct payment minus value received. Charity must disclose if >$75.",
      "calculationRequired": false,
      "timeEstimateSeconds": 75
    },
    {
      "id": "reg-003-024",
      "section": "REG",
      "topic": "Individual Taxation",
      "subtopic": "Itemized Deductions",
      "conceptTested": "Ordinary income property contributions",
      "difficulty": "hard",
      "questionFormat": "MCQ",
      "question": "When contributing ordinary income property to charity, the deduction is limited to:",
      "options": {
        "A": "Fair market value",
        "B": "The taxpayer's basis in the property",
        "C": "30% of AGI",
        "D": "The original cost"
      },
      "correctAnswer": "B",
      "explanation": "Contributions of ordinary income property (inventory, short-term capital gain property, Section 1245 recapture property) are deductible at the donor's basis, not FMV. This prevents donors from avoiding ordinary income recognition by donating appreciated ordinary income property.",
      "tip": "Ordinary income property donation = basis only (not FMV). No end-run around ordinary income.",
      "calculationRequired": false,
      "timeEstimateSeconds": 75
    },
    {
      "id": "reg-003-025",
      "section": "REG",
      "topic": "Individual Taxation",
      "subtopic": "Itemized Deductions",
      "conceptTested": "Appreciated property election",
      "difficulty": "hard",
      "questionFormat": "MCQ",
      "question": "A taxpayer donating appreciated capital gain property may elect to:",
      "options": {
        "A": "Increase the AGI limitation by paying additional tax",
        "B": "Deduct basis instead of FMV to use the higher cash contribution AGI limit (60%) instead of 30%",
        "C": "Carry back the excess deduction",
        "D": "Treat the property as ordinary income property"
      },
      "correctAnswer": "B",
      "explanation": "Donors of appreciated capital gain property can elect to deduct basis (rather than FMV) to qualify for the higher AGI limitation that applies to cash contributions (60% through 2025) instead of the 30% limit for FMV of appreciated property. Electing basis treatment allows use of the cash contribution AGI limits. This may benefit taxpayers with large donations relative to AGI.",
      "tip": "Appreciated property election: use basis for higher AGI limit. Good if high donation relative to income.",
      "calculationRequired": false,
      "timeEstimateSeconds": 75
    },
    {
      "id": "reg-003-026",
      "section": "REG",
      "topic": "Individual Taxation",
      "subtopic": "Itemized Deductions",
      "conceptTested": "Qualified appraisal requirement",
      "difficulty": "hard",
      "questionFormat": "MCQ",
      "question": "A qualified appraisal is required for noncash charitable contributions exceeding:",
      "options": {
        "A": "$250",
        "B": "$500",
        "C": "$5,000",
        "D": "$10,000"
      },
      "correctAnswer": "C",
      "explanation": "A qualified appraisal by a qualified appraiser is required for noncash contributions exceeding $5,000 (per item or group of similar items). Form 8283 Section B must be completed, and the appraiser must sign it.",
      "tip": "Noncash >$5,000 = qualified appraisal required. Form 8283 Section B.",
      "calculationRequired": false,
      "timeEstimateSeconds": 75
    },
    {
      "id": "reg-003-027",
      "section": "REG",
      "topic": "Individual Taxation",
      "subtopic": "Itemized Deductions",
      "conceptTested": "Conservation easement donations",
      "difficulty": "hard",
      "questionFormat": "MCQ",
      "question": "Qualified conservation contributions of appreciated property are deductible up to:",
      "options": {
        "A": "30% of AGI",
        "B": "50% of AGI with 15-year carryforward",
        "C": "60% of AGI",
        "D": "100% of AGI for farmers and ranchers"
      },
      "correctAnswer": "B",
      "explanation": "Qualified conservation contributions are deductible up to 50% of AGI (100% for qualified farmers and ranchers), with excess carried forward for 15 years instead of the normal 5 years. These are perpetual restrictions on property use for conservation purposes.",
      "tip": "Conservation easements: 50% AGI limit (100% for farmers), 15-year carryforward.",
      "calculationRequired": false,
      "timeEstimateSeconds": 75
    },
    {
      "id": "reg-003-028",
      "section": "REG",
      "topic": "Individual Taxation",
      "subtopic": "Itemized Deductions",
      "conceptTested": "Medical expense for dependents",
      "difficulty": "hard",
      "questionFormat": "MCQ",
      "question": "Medical expenses paid for a dependent are deductible if:",
      "options": {
        "A": "The person was a dependent when the expense was incurred OR paid",
        "B": "The person is currently claimed as a dependent",
        "C": "The taxpayer provides more than half the person's support",
        "D": "The person lived with the taxpayer all year"
      },
      "correctAnswer": "A",
      "explanation": "Medical expenses are deductible if paid for someone who was a dependent either when the medical services were provided or when the expenses were paid. The dependent must meet the relationship and support tests but not necessarily the gross income test.",
      "tip": "Medical for dependent: qualify when services provided OR when paid. Flexible timing.",
      "calculationRequired": false,
      "timeEstimateSeconds": 75
    },
    {
      "id": "reg-003-029",
      "section": "REG",
      "topic": "Individual Taxation",
      "subtopic": "Itemized Deductions",
      "conceptTested": "Long-term care premiums",
      "difficulty": "hard",
      "questionFormat": "MCQ",
      "question": "Long-term care insurance premiums are deductible as medical expenses:",
      "options": {
        "A": "In full regardless of age",
        "B": "Up to age-based limits as a medical expense",
        "C": "Only if the taxpayer is in a nursing home",
        "D": "Only through an employer plan"
      },
      "correctAnswer": "B",
      "explanation": "Qualified long-term care insurance premiums are deductible as a medical expense up to age-based dollar limits (ranging from $480 for ages 40 and under to $5,960 for ages 71+ in 2023). The premiums are then subject to the 7.5% AGI floor.",
      "tip": "LTC insurance premiums: deductible up to age-based limits, then subject to 7.5% floor.",
      "calculationRequired": false,
      "timeEstimateSeconds": 75
    },
    {
      "id": "reg-003-030",
      "section": "REG",
      "topic": "Individual Taxation",
      "subtopic": "Itemized Deductions",
      "conceptTested": "Miscellaneous itemized deductions",
      "difficulty": "hard",
      "questionFormat": "MCQ",
      "question": "Under TCJA, miscellaneous itemized deductions subject to the 2% floor are:",
      "options": {
        "A": "Still deductible for all taxpayers",
        "B": "Suspended and not deductible from 2018-2025",
        "C": "Only deductible for self-employed taxpayers",
        "D": "Limited to $10,000"
      },
      "correctAnswer": "B",
      "explanation": "TCJA suspended miscellaneous itemized deductions subject to the 2% floor from 2018-2025. This includes unreimbursed employee expenses, tax preparation fees, investment expenses, and safe deposit box rental for investment purposes.",
      "tip": "2% floor deductions: GONE through 2025 (employee expenses, tax prep, etc.).",
      "calculationRequired": false,
      "timeEstimateSeconds": 75
    },
    {
      "id": "reg-003-031",
      "section": "REG",
      "topic": "Individual Taxation",
      "subtopic": "Itemized Deductions",
      "conceptTested": "Foreign real property taxes",
      "difficulty": "hard",
      "questionFormat": "MCQ",
      "question": "Foreign real property taxes are:",
      "options": {
        "A": "Deductible as itemized deductions",
        "B": "Not deductible under TCJA (2018-2025)",
        "C": "Deductible only for rental property",
        "D": "Subject to the SALT cap"
      },
      "correctAnswer": "B",
      "explanation": "TCJA eliminated the deduction for foreign real property taxes on personal residences from 2018-2025. However, foreign taxes on investment or rental property remain deductible as business expenses. Foreign income taxes may still be deducted or credited.",
      "tip": "Foreign property taxes on personal residence: not deductible (TCJA). Rental property OK.",
      "calculationRequired": false,
      "timeEstimateSeconds": 75
    },
    {
      "id": "reg-003-032",
      "section": "REG",
      "topic": "Individual Taxation",
      "subtopic": "Itemized Deductions",
      "conceptTested": "Bunching deductions strategy",
      "difficulty": "hard",
      "questionFormat": "MCQ",
      "question": "The 'bunching' strategy for itemized deductions involves:",
      "options": {
        "A": "Spreading deductions evenly across years",
        "B": "Accelerating or deferring deductions to exceed the standard deduction in alternate years",
        "C": "Claiming both standard and itemized deductions",
        "D": "Converting itemized deductions to FOR AGI deductions"
      },
      "correctAnswer": "B",
      "explanation": "Bunching involves timing discretionary deductions (charitable contributions, property taxes, medical procedures) to concentrate them in alternate years, allowing itemization in some years while taking the standard deduction in others. This maximizes total deductions over time.",
      "tip": "Bunching: concentrate deductions in one year to itemize, take standard in off years.",
      "calculationRequired": false,
      "timeEstimateSeconds": 75
    },
    {
      "id": "reg-003-033",
      "section": "REG",
      "topic": "Individual Taxation",
      "subtopic": "Itemized Deductions",
      "conceptTested": "Donor-advised fund contributions",
      "difficulty": "hard",
      "questionFormat": "MCQ",
      "question": "Contributions to a donor-advised fund are:",
      "options": {
        "A": "Not deductible until grants are made to charities",
        "B": "Deductible when made to the fund, subject to public charity limits",
        "C": "Subject to private foundation limits",
        "D": "Limited to $10,000 per year"
      },
      "correctAnswer": "B",
      "explanation": "Contributions to donor-advised funds are deductible when made (not when grants are distributed), subject to public charity AGI limits (60% cash, 30% appreciated property). The donor gives up ownership but can recommend grants. DAFs are useful for bunching deductions.",
      "tip": "DAF contribution: deductible when made (public charity rules). Great for bunching strategy.",
      "calculationRequired": false,
      "timeEstimateSeconds": 75
    },
    {
      "id": "reg-003-034",
      "section": "REG",
      "topic": "Individual Taxation",
      "subtopic": "Itemized Deductions",
      "conceptTested": "Qualified charitable distribution",
      "difficulty": "hard",
      "questionFormat": "MCQ",
      "question": "A qualified charitable distribution (QCD) from an IRA:",
      "options": {
        "A": "Is included in income and then deducted",
        "B": "Is excluded from income and cannot be claimed as a charitable deduction",
        "C": "Is only available to taxpayers under age 70½",
        "D": "Can be made to donor-advised funds"
      },
      "correctAnswer": "B",
      "explanation": "QCDs allow taxpayers age 70½ or older to distribute up to $100,000 directly from an IRA to charity. The distribution is excluded from income (no deduction taken). QCDs can satisfy RMDs and benefit those who don't itemize.",
      "tip": "QCD: excluded from income, satisfies RMD, no deduction. Age 70½+, up to $100K/year.",
      "calculationRequired": false,
      "timeEstimateSeconds": 75
    },
    {
      "id": "reg-003-035",
      "section": "REG",
      "topic": "Individual Taxation",
      "subtopic": "Itemized Deductions",
      "conceptTested": "Pease limitation",
      "difficulty": "hard",
      "questionFormat": "MCQ",
      "question": "The Pease limitation on itemized deductions under current law is:",
      "options": {
        "A": "Still in effect for high-income taxpayers",
        "B": "Suspended from 2018-2025 under TCJA",
        "C": "Only applies to charitable deductions",
        "D": "Set at 3% of AGI over threshold amounts"
      },
      "correctAnswer": "B",
      "explanation": "The Pease limitation (which reduced itemized deductions by 3% of AGI over threshold amounts, up to 80% of certain deductions) was suspended by TCJA from 2018-2025. Currently, itemized deductions are not phased out based on income.",
      "tip": "Pease limitation: SUSPENDED through 2025. No AGI phase-out of itemized deductions.",
      "calculationRequired": false,
      "timeEstimateSeconds": 75
    }
  ]
}
